find_libpython/__init__.py
find_libpython/__main__.py
find_libpython/_version.py
find_libpython-0.3.1.dist-info/LICENSE
find_libpython-0.3.1.dist-info/METADATA
find_libpython-0.3.1.dist-info/WHEEL
find_libpython-0.3.1.dist-info/entry_points.txt
find_libpython-0.3.1.dist-info/top_level.txt
find_libpython-0.3.1.dist-info/RECORD
