Metadata-Version: 2.1
Name: find_libpython
Version: 0.3.1
Summary: Finds the libpython associated with your environment, wherever it may be hiding
Home-page: https://github.com/ktbarrett/find_libpython
Author: Takafumi Arakaki
Maintainer: Kaleb Barrett
Maintainer-email: dev.ktbarrett@gmail.com
License: MIT
Keywords: libpython
Classifier: License :: OSI Approved :: MIT License
Classifier: Programming Language :: Python :: 3
Classifier: Topic :: Software Development :: Libraries
License-File: LICENSE
